dj_sso_client2-1.0.1.dist-info/DESCRIPTION.rst
dj_sso_client2-1.0.1.dist-info/METADATA
dj_sso_client2-1.0.1.dist-info/RECORD
dj_sso_client2-1.0.1.dist-info/WHEEL
dj_sso_client2-1.0.1.dist-info/metadata.json
dj_sso_client2-1.0.1.dist-info/top_level.txt
djssoclient/__init__.py
djssoclient/admin.py
djssoclient/apiclient.py
djssoclient/authbackend.py
djssoclient/models.py
djssoclient/tests.py
djssoclient/urls.py
djssoclient/userstorage.py
djssoclient/version.py
djssoclient/views.py
djssoclient/migrations/0001_initial.py
djssoclient/migrations/__init__.py
