Metadata-Version: 2.0
Name: dj-sso-client2
Version: 1.0.1
Summary: A Django SSO client application, works with dj-sso-server
Home-page: https://github.com/tofu0913/dj-sso-client
Author: Fan Fei, Cliff Chen
Author-email: tofu0913@gmail.com
License: GPL v2.0
Platform: UNKNOWN
Classifier: Environment :: Web Environment
Classifier: Framework :: Django
Classifier: Intended Audience :: Developers
Classifier: License :: OSI Approved :: GNU General Public License v2 (GPLv2)
Classifier: Operating System :: OS Independent
Classifier: Programming Language :: Python
Classifier: Programming Language :: Python :: 3.4
Classifier: Topic :: Internet :: WWW/HTTP
Classifier: Topic :: Internet :: WWW/HTTP :: Dynamic Content
